LICENSE
MANIFEST.in
Makefile
README.md
audit_requirements.txt
doc_requirements.txt
requirements.txt
setup.py
test_requirements.txt
tox.ini
sshpool/__init__.py
sshpool/channel.py
sshpool/client.py
sshpool/ctl.py
sshpool/rest.py
sshpool/sshpoolctl.py
sshpool/sshpoold.py
sshpool.egg-info/PKG-INFO
sshpool.egg-info/SOURCES.txt
sshpool.egg-info/dependency_links.txt
sshpool.egg-info/entry_points.txt
sshpool.egg-info/requires.txt
sshpool.egg-info/top_level.txt
tests/__init__.py
tests/test_api.py
tests/test_channel.py
tests/utils.py