Metadata-Version: 1.0
Name: sshpool
Version: 0.1.2
Summary: Manage persistent pool of SSH channels accessible via RESTful API and command line utility
Home-page: https://github.com/abhinavsingh/sshpool
Author: Abhinav Singh
Author-email: mailsforabhinav@gmail.com
License: BSD
Platform: UNKNOWN
Classifier: Development Status :: 4 - Beta
Classifier: Environment :: Console
Classifier: Intended Audience :: Developers
Classifier: Intended Audience :: System Administrators
Classifier: License :: OSI Approved :: BSD License
Classifier: Operating System :: MacOS
Classifier: Operating System :: POSIX
Classifier: Operating System :: Unix
Classifier: Programming Language :: Python :: 2.7
Classifier: Topic :: Utilities
